macosko2015/__init__.py
macosko2015/main.py
macosko2015-2.0.2.dist-info/DESCRIPTION.rst
macosko2015-2.0.2.dist-info/METADATA
macosko2015-2.0.2.dist-info/RECORD
macosko2015-2.0.2.dist-info/WHEEL
macosko2015-2.0.2.dist-info/metadata.json
macosko2015-2.0.2.dist-info/top_level.txt
